tor_with_requests.py
tor_with_requests/tor_with_requests.py
tor_with_requests-1.0.dist-info/METADATA
tor_with_requests-1.0.dist-info/WHEEL
tor_with_requests-1.0.dist-info/top_level.txt
tor_with_requests-1.0.dist-info/RECORD
